COPYING
INSTALL
MANIFEST.in
NEWS
README.rst
cy_build.py
pysam.py
requirements.txt
setup.cfg
setup.py
bcftools/HMM.c
bcftools/HMM.c.pysam.c
bcftools/HMM.h
bcftools/bam2bcf.c
bcftools/bam2bcf.c.pysam.c
bcftools/bam2bcf.h
bcftools/bam2bcf_indel.c
bcftools/bam2bcf_indel.c.pysam.c
bcftools/bam_sample.c
bcftools/bam_sample.c.pysam.c
bcftools/bam_sample.h
bcftools/bcftools.h
bcftools/bcftools.pysam.c
bcftools/bcftools.pysam.h
bcftools/bin.c
bcftools/bin.c.pysam.c
bcftools/bin.h
bcftools/call.h
bcftools/ccall.c
bcftools/ccall.c.pysam.c
bcftools/consensus.c
bcftools/consensus.c.pysam.c
bcftools/convert.c
bcftools/convert.c.pysam.c
bcftools/convert.h
bcftools/csq.c
bcftools/csq.c.pysam.c
bcftools/em.c
bcftools/em.c.pysam.c
bcftools/filter.c
bcftools/filter.c.pysam.c
bcftools/filter.h
bcftools/gvcf.c
bcftools/gvcf.c.pysam.c
bcftools/gvcf.h
bcftools/hclust.c
bcftools/hclust.c.pysam.c
bcftools/hclust.h
bcftools/khash_str2str.h
bcftools/kheap.h
bcftools/kmin.c
bcftools/kmin.c.pysam.c
bcftools/kmin.h
bcftools/main.c
bcftools/main.c.pysam.c
bcftools/mcall.c
bcftools/mcall.c.pysam.c
bcftools/mpileup.c
bcftools/mpileup.c.pysam.c
bcftools/mw.h
bcftools/ploidy.c
bcftools/ploidy.c.pysam.c
bcftools/ploidy.h
bcftools/prob1.c
bcftools/prob1.c.pysam.c
bcftools/prob1.h
bcftools/rbuf.h
bcftools/regidx.c
bcftools/regidx.c.pysam.c
bcftools/regidx.h
bcftools/reheader.c
bcftools/reheader.c.pysam.c
bcftools/smpl_ilist.c
bcftools/smpl_ilist.c.pysam.c
bcftools/smpl_ilist.h
bcftools/tabix.c
bcftools/tabix.c.pysam.c
bcftools/tsv2vcf.c
bcftools/tsv2vcf.c.pysam.c
bcftools/tsv2vcf.h
bcftools/vcfannotate.c
bcftools/vcfannotate.c.pysam.c
bcftools/vcfbuf.c
bcftools/vcfbuf.c.pysam.c
bcftools/vcfbuf.h
bcftools/vcfcall.c
bcftools/vcfcall.c.pysam.c
bcftools/vcfcnv.c
bcftools/vcfcnv.c.pysam.c
bcftools/vcfconcat.c
bcftools/vcfconcat.c.pysam.c
bcftools/vcfconvert.c
bcftools/vcfconvert.c.pysam.c
bcftools/vcffilter.c
bcftools/vcffilter.c.pysam.c
bcftools/vcfgtcheck.c
bcftools/vcfgtcheck.c.pysam.c
pysam_cabbage.egg-info/PKG-INFO
pysam_cabbage.egg-info/SOURCES.txt
pysam_cabbage.egg-info/dependency_links.txt
pysam_cabbage.egg-info/not-zip-safe
pysam_cabbage.egg-info/top_level.txt
