Metadata-Version: 1.1
Name: pysam-cabbage
Version: 0.15.3
Summary: pysam
Home-page: https://github.com/pysam-developers/pysam
Author: Andreas Heger
Author-email: andreas.heger@gmail.com
License: MIT
Platform: POSIX
Platform: UNIX
Platform: MacOS
Classifier: Development Status :: 4 - Beta
Classifier: Intended Audience :: Science/Research
Classifier: Intended Audience :: Developers
Classifier: License :: OSI Approved
Classifier: Programming Language :: Python
Classifier: Topic :: Software Development
Classifier: Topic :: Scientific/Engineering
Classifier: Operating System :: POSIX
Classifier: Operating System :: Unix
Classifier: Operating System :: MacOS
Requires: cython (>=0.21)
